voxceleb_luigi/__init__.py
voxceleb_luigi/atomized_local_target.py
voxceleb_luigi/download_audio.py
voxceleb_luigi/download_data.py
voxceleb_luigi/extract_data.py
voxceleb_luigi/extract_segment.py
voxceleb_luigi/ffmpeg.py
voxceleb_luigi/process_directory.py
voxceleb_luigi/process_people.py
voxceleb_luigi/process_person.py
voxceleb_luigi/process_video_for_person.py
voxceleb_luigi/soft_failure.py
voxceleb_luigi/util.py
voxceleb_luigi-0.2.0.dist-info/DESCRIPTION.rst
voxceleb_luigi-0.2.0.dist-info/METADATA
voxceleb_luigi-0.2.0.dist-info/RECORD
voxceleb_luigi-0.2.0.dist-info/WHEEL
voxceleb_luigi-0.2.0.dist-info/metadata.json
voxceleb_luigi-0.2.0.dist-info/top_level.txt
