Metadata-Version: 2.0
Name: voxceleb-luigi
Version: 0.2.0
Summary: Luigi pipeline to download VoxCeleb audio from YouTube and extract speaker segments
Home-page: https://github.com/maxhollmann/voxceleb-luigi
Author: Max Hollmann
License: MIT
Platform: UNKNOWN
Classifier: License :: OSI Approved :: MIT License
Classifier: Development Status :: 4 - Beta
Classifier: Environment :: Console
Classifier: Programming Language :: Python
Classifier: Programming Language :: Python :: 3
Classifier: Programming Language :: Python :: 3 :: Only
Classifier: Programming Language :: Python :: 3.6
Classifier: Topic :: Multimedia
Classifier: Topic :: Multimedia :: Sound/Audio
Classifier: Topic :: Multimedia :: Sound/Audio :: Speech
Requires-Dist: luigi
